{"id":"..\\node_modules\\leancloud-storage\\dist\\node\\polyfills\\index.js","dependencies":[{"name":"C:\\Users\\Administrator\\Desktop\\163-music-demo\\node_modules\\leancloud-storage\\package.json","includedInParent":true,"mtime":1537089220121},{"name":"C:\\Users\\Administrator\\Desktop\\163-music-demo\\package.json","includedInParent":true,"mtime":1537267500494}],"generated":{"js":"\"use strict\";","map":{"mappings":[{"source":"..\\node_modules\\leancloud-storage\\dist\\node\\polyfills\\index.js","original":{"line":1,"column":0},"generated":{"line":1,"column":0}}],"sources":{"..\\node_modules\\leancloud-storage\\dist\\node\\polyfills\\index.js":"\"use strict\";"},"lineCount":1}},"hash":"0f1397bf76665e579432049d00786ef0","cacheData":{"env":{}}}